cppy/__init__.py
cppy/version.py
cppy/include/cppy/cppy.h
cppy/include/cppy/defines.h
cppy/include/cppy/errors.h
cppy/include/cppy/ptr.h
cppy-1.2.1.dist-info/LICENSE
cppy-1.2.1.dist-info/METADATA
cppy-1.2.1.dist-info/WHEEL
cppy-1.2.1.dist-info/top_level.txt
cppy-1.2.1.dist-info/RECORD
