Metadata-Version: 2.1
Name: cppy
Version: 1.2.1
Summary: UNKNOWN
Home-page: https://github.com/nucleic/cppy
Author-email: The Nucleic Development Team <sccolbert@gmail.com>
Maintainer-email: "Matthieu C. Dartiailh" <m.dartiailh@gmail.com>
License: Copyright (c) 2014, Nucleic
Project-URL: homepage, https://github.com/nucleic/cppy
Project-URL: documentation, https://cppy.readthedocs.io/en/latest/
Project-URL: repository, https://github.com/nucleic/cppy
Project-URL: changelog, https://github.com/nucleic/cppy/blob/main/releasenotes.rst
Platform: UNKNOWN
Classifier: License :: OSI Approved :: BSD License
Classifier: Programming Language :: Python
Classifier: Programming Language :: Python :: 3
Classifier: Programming Language :: Python :: 3.7
Classifier: Programming Language :: Python :: 3.8
Classifier: Programming Language :: Python :: 3.9
Classifier: Programming Language :: Python :: 3.10
Classifier: Programming Language :: Python :: Implementation :: CPython
Requires-Python: >=3.7
License-File: LICENSE
